mailhub/__init__.py
mailhub/mailhub.py
mailhub-1.0.0.dist-info/licenses/LICENSE
mailhub-1.0.0.dist-info/METADATA
mailhub-1.0.0.dist-info/WHEEL
mailhub-1.0.0.dist-info/top_level.txt
mailhub-1.0.0.dist-info/RECORD
